cli/analytics_cli.py
cli/pypxml_cli.py
cli/regularize_cli.py
cli/util.py
pypxml/__init__.py
pypxml/pageelement.py
pypxml/pagetype.py
pypxml/pagexml.py
resources/schema.json
pypxml-4.3.1.dist-info/METADATA
pypxml-4.3.1.dist-info/WHEEL
pypxml-4.3.1.dist-info/entry_points.txt
pypxml-4.3.1.dist-info/licenses/LICENSE
pypxml-4.3.1.dist-info/RECORD
