Metadata-Version: 2.4
Name: pypxml
Version: 4.3.1
Summary: A python library for parsing, converting and modifying PageXML files. 
Project-URL: Homepage, https://www.uni-wuerzburg.de/zpd/
Project-URL: Repository, https://github.com/jahtz/pypxml
Author: Centre for Philology and Digitality (ZPD), University of Würzburg
Author-email: Janik Haitz <jahtz.dev@proton.me>
License-Expression: Apache-2.0
License-File: LICENSE
Keywords: PageXML,XML
Classifier: License :: OSI Approved :: Apache Software License
Classifier: Operating System :: OS Independent
Classifier: Programming Language :: Python :: 3
Requires-Python: >=3.11
Requires-Dist: click~=8.1.8
Requires-Dist: lxml~=5.4.0
Requires-Dist: rich~=14.0.0
